{
  "Argentonnay": "79013",
  "Aigonnay": "79004",
  "Ardilleux": "79011",
  "Asnières-en-Poitou": "79015",
  "Aubigné": "79018",
  "Bataille": "79027",
  "Beaussais-Vitré": "79030",
  "Bouin": "79045",
  "Brieuil-sur-Chizé": "79055",
  "Brioux-sur-Boutonne": "79057",
  "Caunay": "79060",
  "Celles-sur-Belle": "79061",
  "Chail": "79064",
  "Chapelle-Pouilloux": "79074",
  "Chef-Boutonne": "79083",
  "Chenay": "79084",
  "Chérigné": "79085",
  "Chey": "79087",
  "Chizé": "79090",
  "Clussais-la-Pommeraie": "79095",
  "Couarde": "79098",
  "Couture-d'Argenson": "79106",
  "Crézières": "79107",
  "Ensigné": "79111",
  "Exoudun": "79115",
  "Fontenille-Saint-Martin-d'Entraigues": "79122",
  "Fosses": "79126",
  "Fressines": "79129",
  "Alloinay": "79136",
  "Hanc": "79140",
  "Juillé": "79142",
  "Lezay": "79148",
  "Limalonges": "79150",
  "Lorigné": "79152",
  "Loubigné": "79153",
  "Loubillé": "79154",
  "Luché-sur-Brioux": "79158",
  "Lusseray": "79160",
  "Mairé-Levescault": "79163",
  "Maisonnay": "79164",
  "Mazières-sur-Béronne": "79173",
  "Melle": "79174",
  "Melleran": "79175",
  "Messé": "79177",
  "Montalembert": "79180",
  "Mothe-Saint-Héray": "79184",
  "Mougon-Thorigné": "79185",
  "Paizay-le-Chapt": "79198",
  "Paizay-le-Tort": "79199",
  "Périgné": "79204",
  "Pers": "79205",
  "Pioussay": "79211",
  "Pliboux": "79212",
  "Pouffonds": "79214",
  "Prailles": "79217",
  "Rom": "79230",
  "Sainte-Blandine": "79240",
  "Saint-Coutant": "79243",
  "Saint-Génard": "79251",
  "Saint-Léger-de-la-Martinière": "79264",
  "Saint-Martin-lès-Melle": "79279",
  "Saint-Médard": "79282",
  "Saint-Romans-lès-Melle": "79295",
  "Sainte-Soline": "79297",
  "Saint-Vincent-la-Châtre": "79301",
  "Sauzé-Vaussais": "79307",
  "Secondigné-sur-Belle": "79310",
  "Séligné": "79312",
  "Sepvret": "79313",
  "Sompt": "79314",
  "Tillou": "79330",
  "Vançais": "79336",
  "Vanzay": "79338",
  "Vernoux-sur-Boutonne": "79343",
  "Vert": "79346",
  "Villefollet": "79348",
  "Villemain": "79349",
  "Villiers-en-Bois": "79350",
  "Villiers-sur-Chizé": "79352",
  "Missé": "79178",
  "Tourtenay": "79331",
  "Bouillé-Loretz": "79043",
  "Bressuire": "79049",
  "Val en Vignes": "79063",
  "Mauléon": "79079",
  "Combrand": "79096",
  "Coulonges-Thouarsais": "79102",
  "Genneton": "79132",
  "Luché-Thouarsais": "79159",
  "Mauzé-Thouarsais": "79171",
  "Nueil-les-Aubiers": "79195",
  "Petite-Boissière": "79207",
  "Pin": "79210",
  "Saint-Amand-sur-Sèvre": "79235",
  "Saint-Aubin-du-Plain": "79238",
  "Voulmentin": "79242",
  "Sainte-Gemme": "79250",
  "Saint Maurice Étusson": "79280",
  "Saint-Pierre-des-Échaubrognes": "79289",
  "Puihardy": "79223",
  "Trayes": "79332",
  "Absie": "79001",
  "Adilly": "79002",
  "Allonne": "79007",
  "Amailloux": "79008",
  "Ardin": "79012",
  "Augé": "79020",
  "Azay-sur-Thouet": "79025",
  "Béceleuf": "79032",
  "Beugnon": "79035",
  "Boismé": "79038",
  "Boissière-en-Gâtine": "79040",
  "Boussais": "79047",
  "Bretignolles": "79050",
  "Breuil-Bernard": "79051",
  "Busseau": "79059",
  "Cerizay": "79062",
  "Champdeniers-Saint-Denis": "79066",
  "Chanteloup": "79069",
  "Chapelle-Bâton": "79070",
  "Chapelle-Saint-Étienne": "79075",
  "Chapelle-Saint-Laurent": "79076",
  "Chapelle-Thireuil": "79077",
  "Châtillon-sur-Thouet": "79080",
  "Chiché": "79088",
  "Cirières": "79091",
  "Clessé": "79094",
  "Coulonges-sur-l'Autize": "79101",
  "Courlay": "79103",
  "Cours": "79104",
  "Faye-l'Abbesse": "79116",
  "Faye-sur-Ardin": "79117",
  "Fénery": "79118",
  "Fenioux": "79119",
  "Forêt-sur-Sèvre": "79123",
  "Geay": "79131",
  "Germond-Rouvre": "79133",
  "Glénay": "79134",
  "Groseillers": "79139",
  "Lageon": "79145",
  "Largeasse": "79147",
  "Maisontiers": "79165",
  "Mazières-en-Gâtine": "79172",
  "Moncoutant": "79179",
  "Montravers": "79183",
  "Moutiers-sous-Chantemerle": "79188",
  "Neuvy-Bouin": "79190",
  "Pamplie": "79200",
  "Parthenay": "79202",
  "Pierrefitte": "79209",
  "Pougne-Hérisson": "79215",
  "Pugny": "79222",
  "Retail": "79226",
  "Saint-André-sur-Sèvre": "79236",
  "Saint-Aubin-le-Cloud": "79239",
  "Saint-Christophe-sur-Roc": "79241",
  "Saint-Georges-de-Noisné": "79253",
  "Saint-Germain-de-Longue-Chaume": "79255",
  "Saint-Jouin-de-Milly": "79261",
  "Saint-Laurs": "79263",
  "Saint-Maixent-de-Beugné": "79269",
  "Saint-Marc-la-Lande": "79271",
  "Sainte-Ouenne": "79284",
  "Saint-Pardoux": "79285",
  "Saint-Paul-en-Gâtine": "79286",
  "Saint-Pompain": "79290",
  "Scillé": "79309",
  "Secondigny": "79311",
  "Soutiers": "79318",
  "Surin": "79320",
  "Tallud": "79322",
  "Vernoux-en-Gâtine": "79342",
  "Verruyes": "79345",
  "Viennay": "79347",
  "Villiers-en-Plaine": "79351",
  "Vouhé": "79354",
  "Xaintray": "79357",
  "Argenton-l'Église": "79014",
  "Brie": "79054",
  "Brion-près-Thouet": "79056",
  "Louzy": "79157",
  "Luzay": "79161",
  "Oiron": "79196",
  "Pas-de-Jeu": "79203",
  "Saint-Cyr-la-Lande": "79244",
  "Saint-Généroux": "79252",
  "Saint-Jacques-de-Thouars": "79258",
  "Saint-Jean-de-Thouars": "79259",
  "Saint-Jouin-de-Marnes": "79260",
  "Saint-Léger-de-Montbrun": "79265",
  "Saint-Martin-de-Mâcon": "79274",
  "Saint-Martin-de-Sanzay": "79277",
  "Sainte-Radegonde": "79292",
  "Saint-Varent": "79299",
  "Sainte-Verge": "79300",
  "Taizé-Maulais": "79321",
  "Thouars": "79329",
  "Airvault": "79005",
  "Assais-les-Jumeaux": "79016",
  "Aubigny": "79019",
  "Availles-Thouarsais": "79022",
  "Beaulieu-sous-Parthenay": "79029",
  "Chantecorps": "79068",
  "Chapelle-Bertrand": "79071",
  "Chillou": "79089",
  "Clavé": "79092",
  "Coutières": "79105",
  "Doux": "79108",
  "Exireuil": "79114",
  "Ferrière-en-Parthenay": "79120",
  "Fomperron": "79121",
  "Forges": "79124",
  "Gourgé": "79135",
  "Irais": "79141",
  "Lhoumois": "79149",
  "Louin": "79156",
  "Marnes": "79167",
  "Ménigoute": "79176",
  "Nanteuil": "79189",
  "Oroux": "79197",
  "Peyratte": "79208",
  "Pompaire": "79213",
  "Pressigny": "79218",
  "Reffannes": "79225",
  "Saint-Germier": "79256",
  "Saint-Lin": "79267",
  "Saint-Loup-Lamairé": "79268",
  "Saint-Martin-du-Fouilloux": "79278",
  "Saivres": "79302",
  "Saurais": "79306",
  "Soudan": "79316",
  "Tessonnière": "79325",
  "Thénezay": "79326",
  "Vasles": "79339",
  "Vausseroux": "79340",
  "Vautebis": "79341",
  "Avon": "79023",
  "Azay-le-Brûlé": "79024",
  "Bougon": "79042",
  "Crèche": "79048",
  "Pamproux": "79201",
  "Romans": "79231",
  "Sainte-Eanne": "79246",
  "Saint-Maixent-l'École": "79270",
  "Saint-Martin-de-Saint-Maixent": "79276",
  "Sainte-Néomaye": "79283",
  "Salles": "79303",
  "Souvigné": "79319",
  "Thorigny-sur-le-Mignon": "79328",
  "Aiffres": "79003",
  "Amuré": "79009",
  "Arçais": "79010",
  "Beauvoir-sur-Niort": "79031",
  "Bessines": "79034",
  "Bourdet": "79046",
  "Brûlain": "79058",
  "Plaine-d'Argenson": "79078",
  "Chauray": "79081",
  "Cherveux": "79086",
  "Coulon": "79100",
  "Échiré": "79109",
  "Épannes": "79112",
  "Fors": "79125",
  "Foye-Monjault": "79127",
  "François": "79128",
  "Frontenay-Rohan-Rohan": "79130",
  "Granzay-Gript": "79137",
  "Juscorps": "79144",
  "Magné": "79162",
  "Marigny": "79166",
  "Mauzé-sur-le-Mignon": "79170",
  "Niort": "79191",
  "Prahecq": "79216",
  "Priaires": "79219",
  "Prin-Deyrançon": "79220",
  "Rochénard": "79229",
  "Saint-Gelais": "79249",
  "Saint-Georges-de-Rex": "79254",
  "Saint-Hilaire-la-Palud": "79257",
  "Saint-Martin-de-Bernegoue": "79273",
  "Saint-Maxire": "79281",
  "Saint-Rémy": "79293",
  "Saint-Romans-des-Champs": "79294",
  "Saint-Symphorien": "79298",
  "Sansais": "79304",
  "Sciecq": "79308",
  "Usseau": "79334",
  "Vallans": "79335",
  "Vanneau-Irleau": "79337",
  "Vouillé": "79355"
}